epg_downloader/__init__.py
epg_downloader/app.py
epg_downloader/cli.py
epg_downloader/clients.py
epg_downloader/epg_downloader.py
epg_downloader/models.py
epg_downloader/utils.py
epg_downloader-0.5.5.dist-info/AUTHORS.rst
epg_downloader-0.5.5.dist-info/LICENSE
epg_downloader-0.5.5.dist-info/METADATA
epg_downloader-0.5.5.dist-info/WHEEL
epg_downloader-0.5.5.dist-info/entry_points.txt
epg_downloader-0.5.5.dist-info/top_level.txt
epg_downloader-0.5.5.dist-info/RECORD
